comparator.v

module comparator(
   input x,
   input y,
   output z
   );
     
   assign z = (~x & ~y) |(x & y);
     
endmodule

stimulus.v

`timescale 1ns / 1ps
module stimulus;
	reg x;
	reg y;
	wire z;
	comparator dut (
		.x(x), 
		.y(y), 
		.z(z)
	);
 
	initial
           begin
           $dumpfile("test.vcd");
           $dumpvars(0,stimulus);

 	   x = 0;
	   y = 0;
	   #20 y = 1;
	   #20 y = 0;		  
	   #80;
           end  
 
	initial
           begin
	   $monitor("x=%d,y=%d,z=%d \n",x,y,z);
	   end
 
        always #10 x = ~x;

	initial #2000 $finish;
endmodule

test.vcd
$date
	Tue May 17 11:55:06 2022
$end
$version
	Icarus Verilog
$end
$timescale
	1ps
$end
$scope module stimulus $end
$var wire 1 ! z $end
$var reg 1 " x $end
$var reg 1 # y $end
$scope module dut $end
$var wire 1 " x $end
$var wire 1 # y $end
$var wire 1 ! z $end
$upscope $end
$upscope $end
$enddefinitions $end
#0
$dumpvars
0#
0"
1!
$end
#10000
0!
1"
#20000
0"
1#
#30000
1!
1"
#40000
1!
0"
0#
#50000
0!
1"
#60000
1!
0"
#70000
0!
1"
#80000
1!
0"
#90000
0!
1"
#100000
1!
0"
#110000
0!
1"
#120000
1!
0"
#130000
0!
1"
#140000
1!
0"
#150000
0!
1"
#160000
1!
0"
#170000
0!
1"
#180000
1!
0"
#190000
0!
1"
#200000
1!
0"
#210000
0!
1"
#220000
1!
0"
#230000
0!
1"
#240000
1!
0"
#250000
0!
1"
#260000
1!
0"
#270000
0!
1"
#280000
1!
0"
#290000
0!
1"
#300000
1!
0"
#310000
0!
1"
#320000
1!
0"
#330000
0!
1"
#340000
1!
0"
#350000
0!
1"
#360000
1!
0"
#370000
0!
1"
#380000
1!
0"
#390000
0!
1"
#400000
1!
0"
#410000
0!
1"
#420000
1!
0"
#430000
0!
1"
#440000
1!
0"
#450000
0!
1"
#460000
1!
0"
#470000
0!
1"
#480000
1!
0"
#490000
0!
1"
#500000
1!
0"
#510000
0!
1"
#520000
1!
0"
#530000
0!
1"
#540000
1!
0"
#550000
0!
1"
#560000
1!
0"
#570000
0!
1"
#580000
1!
0"
#590000
0!
1"
#600000
1!
0"
#610000
0!
1"
#620000
1!
0"
#630000
0!
1"
#640000
1!
0"
#650000
0!
1"
#660000
1!
0"
#670000
0!
1"
#680000
1!
0"
#690000
0!
1"
#700000
1!
0"
#710000
0!
1"
#720000
1!
0"
#730000
0!
1"
#740000
1!
0"
#750000
0!
1"
#760000
1!
0"
#770000
0!
1"
#780000
1!
0"
#790000
0!
1"
#800000
1!
0"
#810000
0!
1"
#820000
1!
0"
#830000
0!
1"
#840000
1!
0"
#850000
0!
1"
#860000
1!
0"
#870000
0!
1"
#880000
1!
0"
#890000
0!
1"
#900000
1!
0"
#910000
0!
1"
#920000
1!
0"
#930000
0!
1"
#940000
1!
0"
#950000
0!
1"
#960000
1!
0"
#970000
0!
1"
#980000
1!
0"
#990000
0!
1"
#1000000
1!
0"
#1010000
0!
1"
#1020000
1!
0"
#1030000
0!
1"
#1040000
1!
0"
#1050000
0!
1"
#1060000
1!
0"
#1070000
0!
1"
#1080000
1!
0"
#1090000
0!
1"
#1100000
1!
0"
#1110000
0!
1"
#1120000
1!
0"
#1130000
0!
1"
#1140000
1!
0"
#1150000
0!
1"
#1160000
1!
0"
#1170000
0!
1"
#1180000
1!
0"
#1190000
0!
1"
#1200000
1!
0"
#1210000
0!
1"
#1220000
1!
0"
#1230000
0!
1"
#1240000
1!
0"
#1250000
0!
1"
#1260000
1!
0"
#1270000
0!
1"
#1280000
1!
0"
#1290000
0!
1"
#1300000
1!
0"
#1310000
0!
1"
#1320000
1!
0"
#1330000
0!
1"
#1340000
1!
0"
#1350000
0!
1"
#1360000
1!
0"
#1370000
0!
1"
#1380000
1!
0"
#1390000
0!
1"
#1400000
1!
0"
#1410000
0!
1"
#1420000
1!
0"
#1430000
0!
1"
#1440000
1!
0"
#1450000
0!
1"
#1460000
1!
0"
#1470000
0!
1"
#1480000
1!
0"
#1490000
0!
1"
#1500000
1!
0"
#1510000
0!
1"
#1520000
1!
0"
#1530000
0!
1"
#1540000
1!
0"
#1550000
0!
1"
#1560000
1!
0"
#1570000
0!
1"
#1580000
1!
0"
#1590000
0!
1"
#1600000
1!
0"
#1610000
0!
1"
#1620000
1!
0"
#1630000
0!
1"
#1640000
1!
0"
#1650000
0!
1"
#1660000
1!
0"
#1670000
0!
1"
#1680000
1!
0"
#1690000
0!
1"
#1700000
1!
0"
#1710000
0!
1"
#1720000
1!
0"
#1730000
0!
1"
#1740000
1!
0"
#1750000
0!
1"
#1760000
1!
0"
#1770000
0!
1"
#1780000
1!
0"
#1790000
0!
1"
#1800000
1!
0"
#1810000
0!
1"
#1820000
1!
0"
#1830000
0!
1"
#1840000
1!
0"
#1850000
0!
1"
#1860000
1!
0"
#1870000
0!
1"
#1880000
1!
0"
#1890000
0!
1"
#1900000
1!
0"
#1910000
0!
1"
#1920000
1!
0"
#1930000
0!
1"
#1940000
1!
0"
#1950000
0!
1"
#1960000
1!
0"
#1970000
0!
1"
#1980000
1!
0"
#1990000
0!
1"
#2000000
1!
0"
